socketrewritten/__init__.py
socketrewritten/main.py
socketrewritten-0.0.1.dist-info/METADATA
socketrewritten-0.0.1.dist-info/WHEEL
socketrewritten-0.0.1.dist-info/top_level.txt
socketrewritten-0.0.1.dist-info/RECORD
