Metadata-Version: 2.1
Name: socketrewritten
Version: 0.0.1
Summary: Simplifing socket module
Home-page: UNKNOWN
Author: Markandpreston
Author-email: <altmarc79@gmail.com>
License: UNKNOWN
Keywords: python,sockets
Platform: UNKNOWN
Classifier: Development Status :: 1 - Planning
Classifier: Intended Audience :: Developers
Classifier: Programming Language :: Python :: 3
Classifier: Operating System :: Unix
Classifier: Operating System :: MacOS :: MacOS X
Classifier: Operating System :: Microsoft :: Windows
